LICENSE.md
MANIFEST.in
README.rst
setup.py
src/nodeconductor_assembly_waldur/__init__.py
src/nodeconductor_assembly_waldur.egg-info/PKG-INFO
src/nodeconductor_assembly_waldur.egg-info/SOURCES.txt
src/nodeconductor_assembly_waldur.egg-info/dependency_links.txt
src/nodeconductor_assembly_waldur.egg-info/entry_points.txt
src/nodeconductor_assembly_waldur.egg-info/not-zip-safe
src/nodeconductor_assembly_waldur.egg-info/requires.txt
src/nodeconductor_assembly_waldur.egg-info/top_level.txt
src/nodeconductor_assembly_waldur/analytics/__init__.py
src/nodeconductor_assembly_waldur/analytics/apps.py
src/nodeconductor_assembly_waldur/analytics/cost_tracking.py
src/nodeconductor_assembly_waldur/analytics/extension.py
src/nodeconductor_assembly_waldur/analytics/handlers.py
src/nodeconductor_assembly_waldur/analytics/openstack.py
src/nodeconductor_assembly_waldur/analytics/slurm.py
src/nodeconductor_assembly_waldur/analytics/tasks.py
src/nodeconductor_assembly_waldur/analytics/utils.py
src/nodeconductor_assembly_waldur/ansible_estimator/__init__.py
src/nodeconductor_assembly_waldur/ansible_estimator/apps.py
src/nodeconductor_assembly_waldur/ansible_estimator/estimator.py
src/nodeconductor_assembly_waldur/ansible_estimator/extension.py
src/nodeconductor_assembly_waldur/ansible_estimator/serializers.py
src/nodeconductor_assembly_waldur/ansible_estimator/urls.py
src/nodeconductor_assembly_waldur/ansible_estimator/views.py
src/nodeconductor_assembly_waldur/billing/__init__.py
src/nodeconductor_assembly_waldur/billing/apps.py
src/nodeconductor_assembly_waldur/billing/exceptions.py
src/nodeconductor_assembly_waldur/billing/extension.py
src/nodeconductor_assembly_waldur/billing/filters.py
src/nodeconductor_assembly_waldur/billing/handlers.py
src/nodeconductor_assembly_waldur/billing/log.py
src/nodeconductor_assembly_waldur/billing/managers.py
src/nodeconductor_assembly_waldur/billing/models.py
src/nodeconductor_assembly_waldur/billing/serializers.py
src/nodeconductor_assembly_waldur/billing/urls.py
src/nodeconductor_assembly_waldur/billing/views.py
src/nodeconductor_assembly_waldur/billing/management/__init__.py
src/nodeconductor_assembly_waldur/billing/management/commands/__init__.py
src/nodeconductor_assembly_waldur/billing/management/commands/rebuild_billing.py
src/nodeconductor_assembly_waldur/billing/migrations/0001_initial.py
