Metadata-Version: 1.1
Name: nodeconductor-assembly-waldur
Version: 2.8.0
Summary: Waldur MasterMind is a hybrid cloud orchestrator.
Home-page: http://waldur.com
Author: OpenNode Team
Author-email: info@opennodecloud.com
License: MIT
Platform: UNKNOWN
Classifier: Framework :: Django
Classifier: Intended Audience :: Developers
Classifier: Intended Audience :: System Administrators
Classifier: Operating System :: OS Independent
Classifier: License :: OSI Approved :: MIT License
